gcloudbearer/__init__.py
gcloudbearer/__main__.py
gcloudbearer/auth.py
bearer_gencloud-1.0.0.dist-info/LICENSE
bearer_gencloud-1.0.0.dist-info/METADATA
bearer_gencloud-1.0.0.dist-info/WHEEL
bearer_gencloud-1.0.0.dist-info/entry_points.txt
bearer_gencloud-1.0.0.dist-info/top_level.txt
bearer_gencloud-1.0.0.dist-info/RECORD
