Metadata-Version: 2.1
Name: bearer-gencloud
Version: 1.0.0
Summary: Token generator for cloud endpoints
Home-page: https://github.com/BrunoTSBuzzo/gcloudbearer
Author: Bruno Buzzo
Author-email: brunobuzzo.dev@gmail.com
License: MIT
Platform: UNKNOWN
Classifier: License :: OSI Approved :: MIT License
Classifier: Programming Language :: Python
Classifier: Programming Language :: Python :: 3
Requires-Dist: google-auth
